LICENSE
MANIFEST.in
README.rst
setup.py
bootstrap_admin/__init__.py
bootstrap_admin/admin.py
bootstrap_admin/static/admin/css/base.css
bootstrap_admin/static/admin/css/bootstrap-responsive.css
bootstrap_admin/static/admin/css/bootstrap-responsive.min.css
bootstrap_admin/static/admin/css/bootstrap.css
bootstrap_admin/static/admin/css/bootstrap.min.css
bootstrap_admin/static/admin/css/change-form.css
bootstrap_admin/static/admin/css/changelists.css
bootstrap_admin/static/admin/css/commons.css
bootstrap_admin/static/admin/css/dashboard.css
bootstrap_admin/static/admin/css/delete-confirmation.css
bootstrap_admin/static/admin/css/forms-and-widgets.css
bootstrap_admin/static/admin/css/forms.css
bootstrap_admin/static/admin/css/login.css
bootstrap_admin/static/admin/img/glyphicons-halflings-white.png
bootstrap_admin/static/admin/img/glyphicons-halflings.png
bootstrap_admin/static/admin/img/logo-140x140.png
bootstrap_admin/static/admin/js/SelectFilter2.js
bootstrap_admin/static/admin/js/actions.js
bootstrap_admin/static/admin/js/actions.min.js
bootstrap_admin/static/admin/js/bootstrap.js
bootstrap_admin/static/admin/js/bootstrap.min.js
bootstrap_admin/static/admin/js/calendar.js
bootstrap_admin/static/admin/js/commons.js
bootstrap_admin/static/admin/js/jquery.js
bootstrap_admin/static/admin/js/jquery.min.js
bootstrap_admin/static/admin/js/admin/DateTimeShortcuts.js
bootstrap_admin/static/bootstrap_admin/config.json
bootstrap_admin/static/bootstrap_admin/css/bootstrap.min.css
bootstrap_admin/static/bootstrap_admin/fonts/glyphicons-halflings-regular.eot
bootstrap_admin/static/bootstrap_admin/fonts/glyphicons-halflings-regular.svg
bootstrap_admin/static/bootstrap_admin/fonts/glyphicons-halflings-regular.ttf
bootstrap_admin/static/bootstrap_admin/fonts/glyphicons-halflings-regular.woff
bootstrap_admin/static/bootstrap_admin/img/logo-140x60.png
bootstrap_admin/static/bootstrap_admin/js/base.js
bootstrap_admin/static/bootstrap_admin/js/bootstrap.min.js
bootstrap_admin_legacy.egg-info/PKG-INFO
bootstrap_admin_legacy.egg-info/SOURCES.txt
bootstrap_admin_legacy.egg-info/dependency_links.txt
bootstrap_admin_legacy.egg-info/not-zip-safe
bootstrap_admin_legacy.egg-info/top_level.txt