Metadata-Version: 1.1
Name: bootstrap-admin-legacy
Version: 0.1.2
Summary: Bootstrap theme for Django admin
Home-page: https://github.com/douglasmiranda/django-admin-bootstrap
Author: alrusdi
Author-email: alrusdi@gmail.com
License: BSD
Keywords: django,admin,skin,theme,bootstrap,responsive
Platform: UNKNOWN
Classifier: Development Status :: 5 - Production/Stable
Classifier: Environment :: Web Environment
Classifier: Framework :: Django
Classifier: Intended Audience :: Developers
Classifier: License :: OSI Approved :: BSD License
Classifier: Operating System :: OS Independent
Classifier: Programming Language :: Python
